salatime/__init__.py
salatime/api_fetcher.py
salatime/prayer.py
salatime/prayer_scheduler.py
salatime/prayer_times_parser.py
salatime/prayers_day.py
salatime-1.0.0.dist-info/LICENSE
salatime-1.0.0.dist-info/METADATA
salatime-1.0.0.dist-info/WHEEL
salatime-1.0.0.dist-info/top_level.txt
salatime-1.0.0.dist-info/RECORD
